odoo8_addon_account_payment_return_import_sepa_pain-8.0.1.0.0.99.dev6-py2.7-nspkg.pth
odoo8_addon_account_payment_return_import_sepa_pain-8.0.1.0.0.99.dev6.dist-info/DESCRIPTION.rst
odoo8_addon_account_payment_return_import_sepa_pain-8.0.1.0.0.99.dev6.dist-info/METADATA
odoo8_addon_account_payment_return_import_sepa_pain-8.0.1.0.0.99.dev6.dist-info/RECORD
odoo8_addon_account_payment_return_import_sepa_pain-8.0.1.0.0.99.dev6.dist-info/WHEEL
odoo8_addon_account_payment_return_import_sepa_pain-8.0.1.0.0.99.dev6.dist-info/metadata.json
odoo8_addon_account_payment_return_import_sepa_pain-8.0.1.0.0.99.dev6.dist-info/namespace_packages.txt
odoo8_addon_account_payment_return_import_sepa_pain-8.0.1.0.0.99.dev6.dist-info/top_level.txt
odoo_addons/account_payment_return_import_sepa_pain/README.rst
odoo_addons/account_payment_return_import_sepa_pain/__init__.py
odoo_addons/account_payment_return_import_sepa_pain/__openerp__.py
odoo_addons/account_payment_return_import_sepa_pain/data/unpaid_reason_codes.xml
odoo_addons/account_payment_return_import_sepa_pain/i18n/account_payment_return_import_sepa_pain.pot
odoo_addons/account_payment_return_import_sepa_pain/i18n/de.po
odoo_addons/account_payment_return_import_sepa_pain/i18n/es.po
odoo_addons/account_payment_return_import_sepa_pain/i18n/sl.po
odoo_addons/account_payment_return_import_sepa_pain/models/__init__.py
odoo_addons/account_payment_return_import_sepa_pain/models/payment_return.py
odoo_addons/account_payment_return_import_sepa_pain/static/description/icon.png
odoo_addons/account_payment_return_import_sepa_pain/static/description/icon.svg
odoo_addons/account_payment_return_import_sepa_pain/test_files/test-sepa-unpaid.xml
odoo_addons/account_payment_return_import_sepa_pain/test_files/test-sepa-unpaid.zip
odoo_addons/account_payment_return_import_sepa_pain/tests/__init__.py
odoo_addons/account_payment_return_import_sepa_pain/tests/test_import_sepa_pain.py
odoo_addons/account_payment_return_import_sepa_pain/wizard/__init__.py
odoo_addons/account_payment_return_import_sepa_pain/wizard/pain_parser.py
odoo_addons/account_payment_return_import_sepa_pain/wizard/payment_return_import.py
