Metadata-Version: 2.0
Name: odoo8-addon-account-payment-return-import-sepa-pain
Version: 8.0.1.0.0.99.dev6
Summary: Module to import SEPA Direct Debit Unpaid Report File Format PAIN.002.001.03
Home-page: https://www.tecnativa.com
Author: Tecnativa,Odoo Community Association (OCA)
Author-email: support@odoo-community.org
License: AGPL-3
Platform: UNKNOWN
Classifier: Programming Language :: Python
Classifier: Framework :: Odoo
Classifier: License :: OSI Approved :: GNU Affero General Public License v3
Requires-Python: ~=2.7
Requires-Dist: odoo (<9.0a,>=8.0a)
Requires-Dist: odoo8-addon-account-banking-payment-export
Requires-Dist: odoo8-addon-account-payment-return-import
